.coveragerc
.travis.yml
AUTHORS
CONTRIBUTING.rst
ChangeLog
Dockerfile
LICENSE
MANIFEST.in
README.rst
docker-compose.yml
requirements.txt
setup.cfg
setup.py
tox.ini
contrib/bootstrap/blog.yaml
contrib/bootstrap/demo.yaml
contrib/django/.env
contrib/django/manage.py
contrib/django/wsgi.py
contrib/gunicorn/server
contrib/haproxy/docker-compose.yml
contrib/nginx/Dockerfile
contrib/nginx/sites-enabled/site.conf
contrib/scripts/install_blog.sh
contrib/scripts/install_leonardo.sh
contrib/scripts/install_leonardo_dev.sh
contrib/scripts/install_store.sh
contrib/supervisor/demo.conf
contrib/supervisor/docker.conf
contrib/supervisor/run.sh
contrib/tornado/server
debian/changelog
debian/compat
debian/control
debian/dirs
debian/docs
debian/install
debian/lithian-overrides
debian/postinst
debian/postrm
debian/rules
debian/templates
debian/triggers
debian/source/format
django_leonardo.egg-info/PKG-INFO
django_leonardo.egg-info/SOURCES.txt
django_leonardo.egg-info/dependency_links.txt
django_leonardo.egg-info/not-zip-safe
django_leonardo.egg-info/pbr.json
django_leonardo.egg-info/requires.txt
django_leonardo.egg-info/top_level.txt
docs/Makefile
docs/make.bat
docs/source/conf.py
docs/source/index.rst
docs/source/readme.rst
docs/source/_static/leonardo_001.png
docs/source/_static/graphml/theme_structure.graphml
docs/source/_static/module/web/leonardo_web_001.png
docs/source/_static/module/web/leonardo_web_002.png
docs/source/_static/svg/theme_structure.svg
docs/source/components/client_side.rst
docs/source/components/live_settings.rst
docs/source/components/messages.rst
docs/source/components/modals.rst
docs/source/components/thumbnails.rst
docs/source/config/config.rst
docs/source/config/languages.rst
docs/source/config/live.rst
docs/source/config/media.rst
docs/source/config/migrations.rst
docs/source/config/search.rst
docs/source/config/themes.rst
docs/source/extends/conf_reference.rst
docs/source/extends/new_module.rst
docs/source/extends/new_site.rst
docs/source/extends/new_theme.rst
docs/source/install/bootstrap.rst
docs/source/install/development.rst
docs/source/install/intro.rst
docs/source/install/production.rst
docs/source/install/salt.rst
docs/source/module/media/settings.rst
docs/source/module/media/usage.rst
